{
  "cached_at": "2026-03-30T08:28:03.751109",
  "data": {
    "ticker": "JPM",
    "cik": "0000019617",
    "10-Q": [
      {
        "form": "10-Q",
        "date": "2025-11-04",
        "accession": "0001628280-25-048859",
        "document": "jpm-20250930.htm"
      },
      {
        "form": "10-Q",
        "date": "2025-08-05",
        "accession": "0000019617-25-000615",
        "document": "jpm-20250630.htm"
      },
      {
        "form": "10-Q",
        "date": "2025-05-01",
        "accession": "0000019617-25-000421",
        "document": "jpm-20250331.htm"
      }
    ],
    "10-K": [
      {
        "form": "10-K",
        "date": "2026-02-13",
        "accession": "0001628280-26-008131",
        "document": "jpm-20251231.htm"
      }
    ],
    "form4": [
      {
        "form": "4",
        "date": "2026-03-27",
        "accession": "0001225208-26-004056",
        "document": "xslF345X06/doc4.xml"
      },
      {
        "form": "4",
        "date": "2026-03-27",
        "accession": "0001225208-26-004055",
        "document": "xslF345X06/doc4.xml"
      },
      {
        "form": "4",
        "date": "2026-03-27",
        "accession": "0001225208-26-004051",
        "document": "xslF345X06/doc4.xml"
      },
      {
        "form": "4",
        "date": "2026-03-27",
        "accession": "0001225208-26-004054",
        "document": "xslF345X06/doc4.xml"
      },
      {
        "form": "4",
        "date": "2026-03-27",
        "accession": "0001225208-26-004050",
        "document": "xslF345X06/doc4.xml"
      },
      {
        "form": "4",
        "date": "2026-03-27",
        "accession": "0001225208-26-004053",
        "document": "xslF345X06/doc4.xml"
      },
      {
        "form": "4",
        "date": "2026-03-27",
        "accession": "0001225208-26-004049",
        "document": "xslF345X06/doc4.xml"
      },
      {
        "form": "4",
        "date": "2026-03-27",
        "accession": "0001225208-26-004052",
        "document": "xslF345X06/doc4.xml"
      },
      {
        "form": "4",
        "date": "2026-03-27",
        "accession": "0001225208-26-004048",
        "document": "xslF345X06/doc4.xml"
      },
      {
        "form": "4",
        "date": "2026-03-27",
        "accession": "0001225208-26-004047",
        "document": "xslF345X06/doc4.xml"
      }
    ],
    "8-K": [
      {
        "form": "8-K",
        "date": "2026-02-23",
        "accession": "0001628280-26-010693",
        "document": "jpm-20260223.htm"
      },
      {
        "form": "8-K",
        "date": "2026-02-05",
        "accession": "0001193125-26-039427",
        "document": "d23804d8k.htm"
      },
      {
        "form": "8-K",
        "date": "2026-01-22",
        "accession": "0000019617-26-000052",
        "document": "jpm-20260120.htm"
      },
      {
        "form": "8-K",
        "date": "2026-01-22",
        "accession": "0001193125-26-019450",
        "document": "d18152d8k.htm"
      },
      {
        "form": "8-K",
        "date": "2026-01-13",
        "accession": "0001628280-26-001915",
        "document": "jpm-20260113.htm"
      }
    ],
    "xbrl_metrics": {
      "revenue": 182447000000,
      "net_income": 57048000000,
      "eps_basic": null,
      "total_assets": 4424900000000,
      "total_debt": 267889000000,
      "operating_cf": -147782000000
    }
  }
}